fspacker/__init__.py
fspacker/cli.py
fspacker/compat.py
fspacker/exceptions.py
fspacker/logger.py
fspacker/py.typed
fspacker/settings.py
fspacker/trackers.py
fspacker/assets/.gitignore
fspacker/assets/ResourceHacker.exe
fspacker/assets/fsloader-cli.exe
fspacker/assets/fsloader-gui.exe
fspacker/assets/tkinter-lib.zip
fspacker/assets/tkinter.zip
fspacker/assets/nsis/COPYING
fspacker/assets/nsis/NSIS.chm
fspacker/assets/nsis/NSIS.exe
fspacker/assets/nsis/build.nsi
fspacker/assets/nsis/default.ico
fspacker/assets/nsis/license_pynsist.txt
fspacker/assets/nsis/makensis.exe
fspacker/assets/nsis/makensisw.exe
fspacker/assets/nsis/nsisconf.nsh
fspacker/assets/nsis/$PLUGINSDIR/System.dll
fspacker/assets/nsis/$PLUGINSDIR/modern-header.bmp
fspacker/assets/nsis/$PLUGINSDIR/modern-wizard.bmp
fspacker/assets/nsis/$PLUGINSDIR/nsDialogs.dll
fspacker/assets/nsis/Bin/GenPat.exe
fspacker/assets/nsis/Bin/MakeLangId.exe
fspacker/assets/nsis/Bin/RegTool-x86.bin
fspacker/assets/nsis/Bin/makensis.exe
fspacker/assets/nsis/Bin/zip2exe.exe
fspacker/assets/nsis/Bin/zlib1.dll
fspacker/assets/nsis/Contrib/Graphics/Checks/big.bmp
fspacker/assets/nsis/Contrib/Graphics/Checks/classic-cross.bmp
fspacker/assets/nsis/Contrib/Graphics/Checks/classic.bmp
fspacker/assets/nsis/Contrib/Graphics/Checks/colorful.bmp
fspacker/assets/nsis/Contrib/Graphics/Checks/grey-cross.bmp
fspacker/assets/nsis/Contrib/Graphics/Checks/grey.bmp
fspacker/assets/nsis/Contrib/Graphics/Checks/modern.bmp
fspacker/assets/nsis/Contrib/Graphics/Checks/red-round.bmp
fspacker/assets/nsis/Contrib/Graphics/Checks/red.bmp
fspacker/assets/nsis/Contrib/Graphics/Checks/simple-round.bmp
fspacker/assets/nsis/Contrib/Graphics/Checks/simple-round2.bmp
fspacker/assets/nsis/Contrib/Graphics/Checks/simple.bmp
fspacker/assets/nsis/Contrib/Graphics/Header/nsis-r.bmp
fspacker/assets/nsis/Contrib/Graphics/Header/nsis.bmp
fspacker/assets/nsis/Contrib/Graphics/Header/nsis3-branding-r.bmp
fspacker/assets/nsis/Contrib/Graphics/Header/nsis3-branding.bmp
fspacker-0.9.29.dist-info/METADATA
fspacker-0.9.29.dist-info/WHEEL
fspacker-0.9.29.dist-info/entry_points.txt
fspacker-0.9.29.dist-info/licenses/AUTHORS.rst
fspacker-0.9.29.dist-info/licenses/LICENSE
fspacker-0.9.29.dist-info/RECORD
