Metadata-Version: 2.4
Name: fspacker
Version: 0.9.29
Summary: Fast & Simple Packer toolset for python.
Project-URL: Documentation, https://fspacker.readthedocs.io/zh-cn/stable/
Project-URL: Issues, https://gitee.com/gooker_young/fspacker/issues
Project-URL: Repository, https://gitee.com/gooker_young/fspacker
Author-email: gooker_young <gooker_young@qq.com>
Maintainer-email: gooker_young <gooker_young@qq.com>
License: MIT license
License-File: AUTHORS.rst
License-File: LICENSE
Classifier: Programming Language :: Python :: 3.8
Classifier: Programming Language :: Python :: 3.9
Classifier: Programming Language :: Python :: Implementation :: CPython
Classifier: Programming Language :: Rust
Requires-Python: >=3.8
Requires-Dist: packaging>=24.2
Requires-Dist: pydantic-settings>=2.8.1
Requires-Dist: pydantic>=2.10.6
Requires-Dist: requests>=2.32.3
Requires-Dist: rich>=13.9.4
Requires-Dist: tomli>=2.2.1
Requires-Dist: typer>=0.15.1
Requires-Dist: urllib3~=1.26.6
Provides-Extra: dev
Requires-Dist: coverage>=7.6.1; extra == 'dev'
Requires-Dist: hatch>=1.14.1; extra == 'dev'
Requires-Dist: pip>=25.0.1; extra == 'dev'
Requires-Dist: pre-commit>=3.5.0; extra == 'dev'
Requires-Dist: pycmd2>=0.5.9; extra == 'dev'
Requires-Dist: pytest-benchmark>=4.0.0; extra == 'dev'
Requires-Dist: pytest-cov>=5.0.0; extra == 'dev'
Requires-Dist: pytest-html>=4.1.1; extra == 'dev'
Requires-Dist: pytest-mock>=3.14.0; extra == 'dev'
Requires-Dist: pytest>=8.3.4; extra == 'dev'
Requires-Dist: ruff>=0.11.12; extra == 'dev'
Requires-Dist: sphinx-autobuild>=2021.3.14; extra == 'dev'
Requires-Dist: sphinx-rtd-theme; extra == 'dev'
Requires-Dist: tox-uv>=1.13.1; extra == 'dev'
Requires-Dist: tox>=4.24.1; extra == 'dev'
Requires-Dist: wheel>=0.45.1; extra == 'dev'
